MANIFEST.in
README.txt
setup.py
giqra/__init__.py
giqra/__main__.py
giqra/gdict.py
giqra/giqra_thread.py
giqra.egg-info/PKG-INFO
giqra.egg-info/SOURCES.txt
giqra.egg-info/dependency_links.txt
giqra.egg-info/requires.txt
giqra.egg-info/top_level.txt
giqra/res/glade/main.glade
giqra/res/plugin/exportdb.py
giqra/res/plugin/importdb.py
giqra/res/plugin/stickers.py
giqra/res/plugin/glade/exportdb.glade
giqra/res/plugin/glade/importdb.glade
giqra/res/plugin/glade/stickers.glade
giqra/res/plugin/translations/mo/ar/LC_MESSAGES/giqra.plugin.exportdb.mo
giqra/res/plugin/translations/mo/ar/LC_MESSAGES/giqra.plugin.importdb.mo
giqra/res/plugin/translations/mo/ar/LC_MESSAGES/giqra.plugin.stickers.mo
giqra/res/plugin/translations/po/giqra.plugin.exportdb.pot
giqra/res/plugin/translations/po/giqra.plugin.importdb.pot
giqra/res/plugin/translations/po/giqra.plugin.stickers.pot
giqra/res/plugin/translations/po/ar/giqra.plugin.exportdb.po
giqra/res/plugin/translations/po/ar/giqra.plugin.importdb.po
giqra/res/plugin/translations/po/ar/giqra.plugin.stickers.po
giqra/res/translations/mo/ar/LC_MESSAGES/giqra.mo
giqra/res/translations/po/giqra.pot
giqra/res/translations/po/ar/giqra.po