Metadata-Version: 1.1
Name: giqra
Version: 1.2
Summary: giqra, a gui for iqra.
Home-page: https://github.com/alghafli/giqra
Author: Mohammad Alghafli
Author-email: thebsom@gmail.com
License: UNKNOWN
Keywords: library management program gui iqra
Platform: UNKNOWN
Classifier: Development Status :: 4 - Beta
Classifier: License :: OSI Approved :: GNU General Public License v3 (GPLv3)
Classifier: Programming Language :: Python :: 3.5
